[{"corporation_id": 1000046, "record_id": 50922690, "start_date": "2019-10-22T04:14:00Z"}, {"corporation_id": 98323701, "record_id": 50278428, "start_date": "2019-07-08T17:39:00Z"}, {"corporation_id": 1000046, "record_id": 49059304, "start_date": "2018-12-29T00:32:00Z"}, {"corporation_id": 98040755, "record_id": 18978205, "start_date": "2012-02-16T06:09:00Z"}, {"corporation_id": 2040840506, "record_id": 18703269, "start_date": "2012-01-11T20:59:00Z"}, {"corporation_id": 98040755, "record_id": 17831321, "start_date": "2011-09-10T03:58:00Z"}, {"corporation_id": 1000046, "record_id": 17818794, "start_date": "2011-09-08T07:12:00Z"}, {"corporation_id": 775889062, "record_id": 17684319, "start_date": "2011-08-20T17:36:00Z"}, {"corporation_id": 145595564, "record_id": 16725705, "start_date": "2011-05-02T16:06:00Z"}, {"corporation_id": 98026391, "is_deleted": true, "record_id": 16284099, "start_date": "2011-03-08T06:29:00Z"}, {"corporation_id": 1000046, "record_id": 16284027, "start_date": "2011-03-08T06:13:00Z"}, {"corporation_id": 1051696120, "record_id": 16240665, "start_date": "2011-03-03T03:46:00Z"}, {"corporation_id": 290155337, "record_id": 16221791, "start_date": "2011-02-28T21:51:00Z"}, {"corporation_id": 1000046, "record_id": 16177751, "start_date": "2011-02-23T23:21:00Z"}, {"corporation_id": 145595564, "record_id": 16130549, "start_date": "2011-02-18T22:25:00Z"}, {"corporation_id": 290155337, "record_id": 15205081, "start_date": "2010-11-04T18:45:00Z"}, {"corporation_id": 1293143425, "record_id": 14564635, "start_date": "2010-08-12T23:39:00Z"}, {"corporation_id": 1000046, "record_id": 14564631, "start_date": "2010-08-12T23:38:00Z"}, {"corporation_id": 1818673405, "record_id": 14535467, "start_date": "2010-08-09T09:37:00Z"}, {"corporation_id": 1000046, "record_id": 14535303, "start_date": "2010-08-09T09:03:00Z"}, {"corporation_id": 1293143425, "record_id": 14461573, "start_date": "2010-07-30T21:45:00Z"}, {"corporation_id": 1000170, "record_id": 14107516, "start_date": "2010-06-21T06:17:00Z"}]