[{"corporation_id": 1000006, "record_id": 38995587, "start_date": "2015-08-07T14:09:00Z"}, {"corporation_id": 98252033, "record_id": 37796806, "start_date": "2015-04-14T16:16:00Z"}, {"corporation_id": 1000006, "record_id": 37777215, "start_date": "2015-04-12T19:18:00Z"}, {"corporation_id": 98252033, "record_id": 37183367, "start_date": "2015-02-22T10:12:00Z"}, {"corporation_id": 1000006, "record_id": 37183354, "start_date": "2015-02-22T10:11:00Z"}, {"corporation_id": 98123154, "record_id": 31560826, "start_date": "2014-03-06T15:28:00Z"}, {"corporation_id": 1000006, "record_id": 31560817, "start_date": "2014-03-06T15:28:00Z"}, {"corporation_id": 575885099, "record_id": 26673859, "start_date": "2013-07-05T14:43:00Z"}, {"corporation_id": 1000006, "record_id": 26330064, "start_date": "2013-06-20T21:30:00Z"}, {"corporation_id": 98123154, "record_id": 23784207, "start_date": "2013-02-24T01:07:00Z"}, {"corporation_id": 1800433803, "record_id": 22989753, "start_date": "2013-02-02T15:20:00Z"}, {"corporation_id": 98118080, "record_id": 19963945, "start_date": "2012-06-09T22:47:00Z"}, {"corporation_id": 1000006, "record_id": 19622918, "start_date": "2012-05-01T10:05:00Z"}, {"corporation_id": 573400667, "record_id": 19207670, "start_date": "2012-03-15T20:27:00Z"}, {"corporation_id": 1800433803, "record_id": 18236834, "start_date": "2011-11-07T06:02:00Z"}, {"corporation_id": 297125146, "record_id": 18146710, "start_date": "2011-10-25T15:39:00Z"}, {"corporation_id": 1311513105, "record_id": 17209457, "start_date": "2011-06-27T00:29:00Z"}, {"corporation_id": 98013265, "record_id": 15754315, "start_date": "2011-01-09T22:11:00Z"}, {"corporation_id": 1800433803, "record_id": 15360528, "start_date": "2010-11-24T19:32:00Z"}, {"corporation_id": 1791474538, "record_id": 15069246, "start_date": "2010-10-16T20:02:00Z"}, {"corporation_id": 1800433803, "record_id": 13160914, "start_date": "2010-03-07T03:28:00Z"}, {"corporation_id": 803755875, "record_id": 11596893, "start_date": "2009-09-20T21:31:00Z"}, {"corporation_id": 1000006, "record_id": 11596886, "start_date": "2009-09-20T21:31:00Z"}, {"corporation_id": 1549067333, "record_id": 11581854, "start_date": "2009-09-19T08:29:00Z"}, {"corporation_id": 1000006, "record_id": 11577525, "start_date": "2009-09-18T19:28:00Z"}, {"corporation_id": 803755875, "record_id": 6971483, "start_date": "2009-02-06T20:43:00Z"}, {"corporation_id": 1000167, "record_id": 6971482, "start_date": "2009-02-05T14:29:00Z"}]