[{"corporation_id": 1000049, "record_id": 40493010, "start_date": "2015-12-21T11:48:00Z"}, {"corporation_id": 98252033, "record_id": 37229423, "start_date": "2015-02-26T18:42:00Z"}, {"corporation_id": 1000049, "record_id": 37229413, "start_date": "2015-02-26T18:41:00Z"}, {"corporation_id": 98123154, "record_id": 24526651, "start_date": "2013-04-02T19:27:00Z"}, {"corporation_id": 98135364, "record_id": 21222365, "start_date": "2012-11-26T10:10:00Z"}, {"corporation_id": 1000049, "record_id": 21217346, "start_date": "2012-11-25T18:24:00Z"}, {"corporation_id": 98008663, "record_id": 19834991, "start_date": "2012-05-26T20:28:00Z"}, {"corporation_id": 1000049, "record_id": 19821883, "start_date": "2012-05-25T15:15:00Z"}, {"corporation_id": 890771429, "record_id": 15135505, "start_date": "2010-10-25T18:34:00Z"}, {"corporation_id": 1000049, "record_id": 15135434, "start_date": "2010-10-25T18:25:00Z"}, {"corporation_id": 1302661108, "is_deleted": true, "record_id": 15117299, "start_date": "2010-10-23T09:00:00Z"}, {"corporation_id": 890771429, "record_id": 14025118, "start_date": "2010-06-12T15:17:00Z"}, {"corporation_id": 1000182, "record_id": 14024964, "start_date": "2010-06-12T14:53:00Z"}, {"corporation_id": 890771429, "record_id": 13963209, "start_date": "2010-06-06T14:32:00Z"}, {"corporation_id": 1000172, "record_id": 13962334, "start_date": "2010-06-06T12:55:00Z"}]