[{"corporation_id": 98504903, "record_id": 47120434, "start_date": "2018-03-07T16:37:00Z"}, {"corporation_id": 1000111, "record_id": 47120422, "start_date": "2018-03-07T16:35:00Z"}, {"corporation_id": 98482430, "record_id": 44947049, "start_date": "2017-05-05T11:17:00Z"}, {"corporation_id": 1000111, "record_id": 44940292, "start_date": "2017-05-04T11:49:00Z"}, {"corporation_id": 1000179, "record_id": 44882899, "start_date": "2017-04-27T09:45:00Z"}, {"corporation_id": 98085082, "record_id": 43976252, "start_date": "2017-01-14T17:34:00Z"}, {"corporation_id": 1000111, "record_id": 42104611, "start_date": "2016-05-27T06:35:00Z"}, {"corporation_id": 98085082, "record_id": 36843824, "start_date": "2015-01-24T18:33:00Z"}, {"corporation_id": 1000111, "record_id": 36819830, "start_date": "2015-01-22T21:44:00Z"}, {"corporation_id": 98146741, "record_id": 25092755, "start_date": "2013-05-09T10:42:00Z"}, {"corporation_id": 98026708, "record_id": 24855772, "start_date": "2013-04-25T05:41:00Z"}, {"corporation_id": 98142591, "record_id": 24423622, "start_date": "2013-03-27T21:26:00Z"}, {"corporation_id": 1000111, "record_id": 14723778, "start_date": "2010-09-02T17:19:00Z"}, {"corporation_id": 174638556, "record_id": 12996041, "start_date": "2010-02-17T17:10:00Z"}, {"corporation_id": 1000111, "record_id": 12995746, "start_date": "2010-02-17T16:28:00Z"}, {"corporation_id": 448917894, "record_id": 7960378, "start_date": "2009-02-04T19:26:00Z"}, {"corporation_id": 1000169, "record_id": 7960377, "start_date": "2009-01-09T22:51:00Z"}]