[{"corporation_id": 1000009, "record_id": 53379977, "start_date": "2020-07-24T20:26:00Z"}, {"corporation_id": 98618888, "is_deleted": true, "record_id": 51028889, "start_date": "2019-11-07T13:40:00Z"}, {"corporation_id": 1000009, "record_id": 51005876, "start_date": "2019-11-04T01:13:00Z"}, {"corporation_id": 98618508, "record_id": 50969726, "start_date": "2019-10-30T04:55:00Z"}, {"corporation_id": 98617015, "is_deleted": true, "record_id": 50937699, "start_date": "2019-10-25T00:05:00Z"}, {"corporation_id": 1000009, "record_id": 50918229, "start_date": "2019-10-21T07:14:00Z"}, {"corporation_id": 98555556, "record_id": 47468390, "start_date": "2018-04-26T23:24:00Z"}, {"corporation_id": 1000009, "record_id": 47373129, "start_date": "2018-04-14T03:38:00Z"}, {"corporation_id": 98489972, "is_deleted": true, "record_id": 43544740, "start_date": "2016-12-11T04:43:00Z"}, {"corporation_id": 1000009, "record_id": 38685713, "start_date": "2015-07-12T17:29:00Z"}, {"corporation_id": 98378979, "record_id": 37541601, "start_date": "2015-03-25T13:20:00Z"}, {"corporation_id": 1000009, "record_id": 37541330, "start_date": "2015-03-25T12:39:00Z"}, {"corporation_id": 98383219, "is_deleted": true, "record_id": 37355192, "start_date": "2015-03-09T02:41:00Z"}, {"corporation_id": 1000009, "record_id": 31043197, "start_date": "2014-02-09T17:18:00Z"}, {"corporation_id": 98066884, "record_id": 27496169, "start_date": "2013-08-09T07:15:00Z"}, {"corporation_id": 1000009, "record_id": 27469861, "start_date": "2013-08-08T02:53:00Z"}, {"corporation_id": 98236241, "record_id": 27414163, "start_date": "2013-08-05T20:18:00Z"}, {"corporation_id": 1000009, "record_id": 27413920, "start_date": "2013-08-05T20:08:00Z"}, {"corporation_id": 98229408, "record_id": 27369671, "start_date": "2013-08-04T03:58:00Z"}, {"corporation_id": 1000009, "record_id": 20869115, "start_date": "2012-10-07T01:46:00Z"}, {"corporation_id": 98040755, "record_id": 20457171, "start_date": "2012-08-11T01:34:00Z"}, {"corporation_id": 1000009, "record_id": 20444498, "start_date": "2012-08-09T09:06:00Z"}, {"corporation_id": 98017206, "record_id": 20444093, "start_date": "2012-08-09T07:14:00Z"}, {"corporation_id": 1000009, "record_id": 20423801, "start_date": "2012-08-06T15:42:00Z"}, {"corporation_id": 98010007, "is_deleted": true, "record_id": 20390176, "start_date": "2012-08-02T02:46:00Z"}, {"corporation_id": 1000009, "record_id": 17765912, "start_date": "2011-08-31T19:37:00Z"}, {"corporation_id": 1373839760, "record_id": 17275223, "start_date": "2011-07-03T21:30:00Z"}, {"corporation_id": 1000009, "record_id": 17273864, "start_date": "2011-07-03T19:01:00Z"}, {"corporation_id": 1267503097, "record_id": 16957665, "start_date": "2011-05-30T13:18:00Z"}, {"corporation_id": 1000009, "record_id": 16847374, "start_date": "2011-05-18T00:36:00Z"}, {"corporation_id": 270227912, "record_id": 16838369, "start_date": "2011-05-16T22:58:00Z"}, {"corporation_id": 1000009, "record_id": 16602472, "start_date": "2011-04-17T03:13:00Z"}, {"corporation_id": 1797542574, "record_id": 14986559, "start_date": "2010-10-06T00:13:00Z"}, {"corporation_id": 1267503097, "record_id": 14659827, "start_date": "2010-08-25T05:03:00Z"}, {"corporation_id": 1000009, "record_id": 14652461, "start_date": "2010-08-24T06:00:00Z"}, {"corporation_id": 1000180, "record_id": 14651623, "start_date": "2010-08-24T02:42:00Z"}, {"corporation_id": 1000009, "record_id": 14646788, "start_date": "2010-08-23T15:11:00Z"}, {"corporation_id": 1000180, "record_id": 14589327, "start_date": "2010-08-16T00:11:00Z"}, {"corporation_id": 1000009, "record_id": 14580837, "start_date": "2010-08-15T00:29:00Z"}, {"corporation_id": 1000180, "record_id": 14580560, "start_date": "2010-08-14T23:42:00Z"}, {"corporation_id": 1000167, "record_id": 14481982, "start_date": "2010-08-02T12:33:00Z"}]