[{"corporation_id": 1000044, "record_id": 55110735, "start_date": "2021-02-19T17:39:00Z"}, {"corporation_id": 98560621, "record_id": 53569903, "start_date": "2020-08-15T00:22:00Z"}, {"corporation_id": 1000009, "record_id": 53569899, "start_date": "2020-08-15T00:22:00Z"}, {"corporation_id": 98296765, "record_id": 51799691, "start_date": "2020-02-10T03:17:00Z"}, {"corporation_id": 1000009, "record_id": 51799690, "start_date": "2020-02-10T03:16:00Z"}, {"corporation_id": 1431056470, "record_id": 47671540, "start_date": "2018-05-26T00:44:00Z"}, {"corporation_id": 98296765, "record_id": 47153136, "start_date": "2018-03-12T06:36:00Z"}, {"corporation_id": 1000009, "record_id": 46368663, "start_date": "2017-11-27T14:16:00Z"}, {"corporation_id": 1705300610, "record_id": 45036618, "start_date": "2017-05-16T04:40:00Z"}, {"corporation_id": 1000009, "record_id": 45020947, "start_date": "2017-05-14T08:55:00Z"}, {"corporation_id": 98296765, "record_id": 43646012, "start_date": "2016-12-18T00:01:00Z"}, {"corporation_id": 1000009, "record_id": 43646009, "start_date": "2016-12-18T00:00:00Z"}, {"corporation_id": 98472091, "record_id": 43590291, "start_date": "2016-12-14T01:05:00Z"}, {"corporation_id": 98296765, "record_id": 43520911, "start_date": "2016-12-09T19:43:00Z"}, {"corporation_id": 1000009, "record_id": 43448676, "start_date": "2016-12-04T19:08:00Z"}, {"corporation_id": 98296765, "record_id": 42991983, "start_date": "2016-11-08T03:51:00Z"}, {"corporation_id": 1000009, "record_id": 42991901, "start_date": "2016-11-08T03:23:00Z"}, {"corporation_id": 98472091, "record_id": 42892745, "start_date": "2016-10-21T01:18:00Z"}, {"corporation_id": 1000009, "record_id": 42892731, "start_date": "2016-10-21T01:15:00Z"}, {"corporation_id": 98054147, "record_id": 42717422, "start_date": "2016-09-17T01:23:00Z"}, {"corporation_id": 1000009, "record_id": 42717378, "start_date": "2016-09-17T01:10:00Z"}, {"corporation_id": 98296765, "record_id": 42608967, "start_date": "2016-08-29T00:25:00Z"}, {"corporation_id": 1000009, "record_id": 42608798, "start_date": "2016-08-28T23:38:00Z"}, {"corporation_id": 98472091, "record_id": 42577839, "start_date": "2016-08-23T03:26:00Z"}, {"corporation_id": 1000009, "record_id": 42577829, "start_date": "2016-08-23T03:24:00Z"}, {"corporation_id": 98296765, "record_id": 42569439, "start_date": "2016-08-21T21:53:00Z"}, {"corporation_id": 1000009, "record_id": 42569430, "start_date": "2016-08-21T21:52:00Z"}, {"corporation_id": 98472091, "record_id": 42549282, "start_date": "2016-08-20T04:09:00Z"}, {"corporation_id": 1000009, "record_id": 42549264, "start_date": "2016-08-20T04:07:00Z"}, {"corporation_id": 98296765, "record_id": 42187474, "start_date": "2016-06-08T04:17:00Z"}, {"corporation_id": 1000009, "record_id": 42187345, "start_date": "2016-06-08T03:57:00Z"}, {"corporation_id": 637427116, "record_id": 37063188, "start_date": "2015-02-11T22:06:00Z"}, {"corporation_id": 1000009, "record_id": 37056897, "start_date": "2015-02-11T07:52:00Z"}, {"corporation_id": 98296765, "record_id": 31649088, "start_date": "2014-03-11T01:05:00Z"}, {"corporation_id": 1000009, "record_id": 31648999, "start_date": "2014-03-11T01:00:00Z"}, {"corporation_id": 637427116, "record_id": 14333559, "start_date": "2010-07-15T17:09:00Z"}, {"corporation_id": 1708482497, "is_deleted": true, "record_id": 14092209, "start_date": "2010-06-19T18:14:00Z"}, {"corporation_id": 1465050528, "record_id": 14067349, "start_date": "2010-06-16T23:05:00Z"}, {"corporation_id": 1708482497, "is_deleted": true, "record_id": 12490105, "start_date": "2009-12-29T05:50:00Z"}, {"corporation_id": 1000009, "record_id": 12170903, "start_date": "2009-11-28T12:10:00Z"}, {"corporation_id": 1077132504, "record_id": 11961462, "start_date": "2009-11-01T17:27:00Z"}, {"corporation_id": 1000044, "record_id": 11648243, "start_date": "2009-09-26T23:28:00Z"}]