[{"corporation_id": 98664915, "record_id": 55450601, "start_date": "2021-04-02T21:45:00Z"}, {"corporation_id": 1000171, "record_id": 55450569, "start_date": "2021-04-02T21:39:00Z"}, {"corporation_id": 98667840, "record_id": 54619814, "start_date": "2020-12-22T18:08:00Z"}, {"corporation_id": 1000060, "record_id": 50944192, "start_date": "2019-10-26T05:22:00Z"}, {"corporation_id": 98342486, "record_id": 48974590, "start_date": "2018-12-14T21:00:00Z"}, {"corporation_id": 1000060, "record_id": 46745709, "start_date": "2018-01-14T15:11:00Z"}, {"corporation_id": 98342486, "record_id": 45150938, "start_date": "2017-05-31T13:16:00Z"}, {"corporation_id": 1000060, "record_id": 45150790, "start_date": "2017-05-31T12:48:00Z"}, {"corporation_id": 98496011, "record_id": 44746225, "start_date": "2017-04-10T20:40:00Z"}, {"corporation_id": 1000060, "record_id": 44662980, "start_date": "2017-03-31T14:09:00Z"}, {"corporation_id": 98496011, "record_id": 44476279, "start_date": "2017-03-08T19:26:00Z"}, {"corporation_id": 1000060, "record_id": 44321802, "start_date": "2017-02-19T16:51:00Z"}, {"corporation_id": 1000182, "record_id": 44310392, "start_date": "2017-02-18T14:03:00Z"}, {"corporation_id": 1000060, "record_id": 44301013, "start_date": "2017-02-17T12:06:00Z"}, {"corporation_id": 98439702, "is_deleted": true, "record_id": 40901118, "start_date": "2016-01-24T21:17:00Z"}, {"corporation_id": 1000060, "record_id": 40901116, "start_date": "2016-01-24T21:16:00Z"}, {"corporation_id": 98378777, "record_id": 40471209, "start_date": "2015-12-19T20:26:00Z"}, {"corporation_id": 1000060, "record_id": 40471181, "start_date": "2015-12-19T20:25:00Z"}, {"corporation_id": 98430189, "is_deleted": true, "record_id": 40209692, "start_date": "2015-11-25T21:18:00Z"}, {"corporation_id": 1000060, "record_id": 40209567, "start_date": "2015-11-25T21:05:00Z"}, {"corporation_id": 98429521, "is_deleted": true, "record_id": 40168147, "start_date": "2015-11-21T16:23:00Z"}, {"corporation_id": 1000060, "record_id": 15091445, "start_date": "2010-10-19T16:19:00Z"}, {"corporation_id": 1420818937, "record_id": 14687560, "start_date": "2010-08-28T21:17:00Z"}, {"corporation_id": 1057676729, "record_id": 14599311, "start_date": "2010-08-17T09:23:00Z"}, {"corporation_id": 1000182, "record_id": 14583765, "start_date": "2010-08-15T11:23:00Z"}, {"corporation_id": 1000171, "record_id": 14562068, "start_date": "2010-08-12T17:29:00Z"}]