[{"corporation_id": 1000060, "record_id": 46832387, "start_date": "2018-01-26T02:54:00Z"}, {"corporation_id": 98491409, "is_deleted": true, "record_id": 46461224, "start_date": "2017-12-09T06:28:00Z"}, {"corporation_id": 1000060, "record_id": 46461110, "start_date": "2017-12-09T06:09:00Z"}, {"corporation_id": 98330748, "record_id": 46350819, "start_date": "2017-11-25T08:33:00Z"}, {"corporation_id": 1000060, "record_id": 44343924, "start_date": "2017-02-22T03:40:00Z"}, {"corporation_id": 98358376, "record_id": 42913700, "start_date": "2016-10-25T00:40:00Z"}, {"corporation_id": 1000060, "record_id": 42911134, "start_date": "2016-10-24T14:25:00Z"}, {"corporation_id": 98454258, "is_deleted": true, "record_id": 42818928, "start_date": "2016-10-07T08:06:00Z"}, {"corporation_id": 1000060, "record_id": 42775299, "start_date": "2016-09-28T03:34:00Z"}, {"corporation_id": 98454258, "is_deleted": true, "record_id": 41794493, "start_date": "2016-04-26T05:29:00Z"}, {"corporation_id": 1000060, "record_id": 41642761, "start_date": "2016-04-11T03:38:00Z"}, {"corporation_id": 98231591, "record_id": 39515112, "start_date": "2015-09-20T23:21:00Z"}, {"corporation_id": 98355872, "record_id": 35990907, "start_date": "2014-11-24T07:40:00Z"}, {"corporation_id": 1000060, "record_id": 35982904, "start_date": "2014-11-23T20:55:00Z"}, {"corporation_id": 1940003502, "record_id": 32671417, "start_date": "2014-05-06T03:51:00Z"}, {"corporation_id": 1000060, "record_id": 32633760, "start_date": "2014-05-04T07:04:00Z"}, {"corporation_id": 98269282, "is_deleted": true, "record_id": 29667663, "start_date": "2013-12-01T22:27:00Z"}, {"corporation_id": 1000060, "record_id": 29444166, "start_date": "2013-11-22T07:03:00Z"}, {"corporation_id": 98231535, "record_id": 28588350, "start_date": "2013-10-06T17:10:00Z"}, {"corporation_id": 1000060, "record_id": 28586153, "start_date": "2013-10-06T15:11:00Z"}, {"corporation_id": 98231535, "record_id": 27160358, "start_date": "2013-07-27T12:32:00Z"}, {"corporation_id": 1000060, "record_id": 27160338, "start_date": "2013-07-27T12:31:00Z"}, {"corporation_id": 98230117, "is_deleted": true, "record_id": 27006100, "start_date": "2013-07-21T01:02:00Z"}, {"corporation_id": 1000060, "record_id": 26809329, "start_date": "2013-07-11T21:38:00Z"}, {"corporation_id": 98226482, "is_deleted": true, "record_id": 26769985, "start_date": "2013-07-09T23:33:00Z"}, {"corporation_id": 1000060, "record_id": 26769936, "start_date": "2013-07-09T23:31:00Z"}, {"corporation_id": 98047361, "record_id": 25913847, "start_date": "2013-06-06T12:58:00Z"}, {"corporation_id": 1000060, "record_id": 20917300, "start_date": "2012-10-14T04:02:00Z"}, {"corporation_id": 851230678, "record_id": 19831316, "start_date": "2012-05-26T13:32:00Z"}, {"corporation_id": 1000060, "record_id": 19830821, "start_date": "2012-05-26T12:22:00Z"}, {"corporation_id": 1546642544, "record_id": 16984674, "start_date": "2011-06-02T22:36:00Z"}, {"corporation_id": 98019195, "record_id": 16759808, "start_date": "2011-05-07T02:25:00Z"}, {"corporation_id": 527405778, "record_id": 14792520, "start_date": "2010-09-11T03:45:00Z"}, {"corporation_id": 876396312, "record_id": 13323654, "start_date": "2010-03-26T08:56:00Z"}, {"corporation_id": 1650001114, "is_deleted": true, "record_id": 13280930, "start_date": "2010-03-21T05:13:00Z"}, {"corporation_id": 1000060, "record_id": 13240078, "start_date": "2010-03-16T05:05:00Z"}, {"corporation_id": 1874303394, "record_id": 12322870, "start_date": "2009-12-13T00:20:00Z"}, {"corporation_id": 1000060, "record_id": 12305960, "start_date": "2009-12-11T12:37:00Z"}, {"corporation_id": 1617226658, "record_id": 12252986, "start_date": "2009-12-06T09:44:00Z"}, {"corporation_id": 1000171, "record_id": 12178438, "start_date": "2009-11-29T04:11:00Z"}]