[{"corporation_id": 98560621, "record_id": 55545833, "start_date": "2021-04-15T15:28:00Z"}, {"corporation_id": 1000167, "record_id": 55518095, "start_date": "2021-04-11T19:44:00Z"}, {"corporation_id": 98293472, "record_id": 47949202, "start_date": "2018-07-05T20:36:00Z"}, {"corporation_id": 1000006, "record_id": 47944114, "start_date": "2018-07-04T22:14:00Z"}, {"corporation_id": 98230658, "record_id": 45369591, "start_date": "2017-07-03T00:31:00Z"}, {"corporation_id": 1000167, "record_id": 45216434, "start_date": "2017-06-09T16:37:00Z"}]