[{"corporation_id": 98040755, "record_id": 50449761, "start_date": "2019-08-01T21:06:00Z"}, {"corporation_id": 1000009, "record_id": 50449758, "start_date": "2019-08-01T21:05:00Z"}, {"corporation_id": 98568018, "record_id": 48171573, "start_date": "2018-08-07T18:32:00Z"}, {"corporation_id": 1000009, "record_id": 48068850, "start_date": "2018-07-24T08:32:00Z"}, {"corporation_id": 98290394, "record_id": 47707667, "start_date": "2018-05-31T07:08:00Z"}, {"corporation_id": 1000009, "record_id": 47707646, "start_date": "2018-05-31T07:05:00Z"}, {"corporation_id": 98536445, "is_deleted": true, "record_id": 47697622, "start_date": "2018-05-29T21:11:00Z"}, {"corporation_id": 1000009, "record_id": 47697613, "start_date": "2018-05-29T21:10:00Z"}, {"corporation_id": 98290394, "record_id": 47621079, "start_date": "2018-05-18T04:00:00Z"}, {"corporation_id": 1000009, "record_id": 44907770, "start_date": "2017-04-30T15:14:00Z"}, {"corporation_id": 98484530, "is_deleted": true, "record_id": 44423243, "start_date": "2017-03-02T19:02:00Z"}, {"corporation_id": 1000045, "record_id": 44416860, "start_date": "2017-03-01T23:40:00Z"}]