[{"corporation_id": 98664915, "record_id": 54406270, "start_date": "2020-11-23T23:20:00Z"}, {"corporation_id": 1000006, "record_id": 54406252, "start_date": "2020-11-23T23:16:00Z"}, {"corporation_id": 98342486, "record_id": 53400329, "start_date": "2020-07-26T19:36:00Z"}, {"corporation_id": 1000006, "record_id": 53400304, "start_date": "2020-07-26T19:33:00Z"}, {"corporation_id": 98647315, "record_id": 53074215, "start_date": "2020-06-20T22:10:00Z"}, {"corporation_id": 1000006, "record_id": 53074214, "start_date": "2020-06-20T22:10:00Z"}, {"corporation_id": 98234298, "record_id": 52118938, "start_date": "2020-03-19T18:56:00Z"}, {"corporation_id": 98617968, "record_id": 52110036, "start_date": "2020-03-18T18:42:00Z"}, {"corporation_id": 1000006, "record_id": 51406502, "start_date": "2019-12-22T04:10:00Z"}, {"corporation_id": 98509551, "record_id": 50613310, "start_date": "2019-08-25T21:39:00Z"}, {"corporation_id": 98603545, "record_id": 50592804, "start_date": "2019-08-22T18:26:00Z"}, {"corporation_id": 98491643, "is_deleted": true, "record_id": 49612880, "start_date": "2019-03-30T19:28:00Z"}, {"corporation_id": 1000006, "record_id": 49612235, "start_date": "2019-03-30T17:43:00Z"}, {"corporation_id": 98553095, "record_id": 49548679, "start_date": "2019-03-19T22:55:00Z"}, {"corporation_id": 1000006, "record_id": 49548673, "start_date": "2019-03-19T22:54:00Z"}, {"corporation_id": 98293472, "record_id": 47720468, "start_date": "2018-06-02T00:21:00Z"}, {"corporation_id": 1000006, "record_id": 47720417, "start_date": "2018-06-02T00:11:00Z"}, {"corporation_id": 98379192, "record_id": 47187112, "start_date": "2018-03-17T15:05:00Z"}, {"corporation_id": 1000006, "record_id": 47187111, "start_date": "2018-03-17T15:05:00Z"}, {"corporation_id": 98491643, "is_deleted": true, "record_id": 46854836, "start_date": "2018-01-28T19:19:00Z"}, {"corporation_id": 98543819, "record_id": 46814206, "start_date": "2018-01-23T19:00:00Z"}, {"corporation_id": 1000006, "record_id": 46662784, "start_date": "2018-01-03T15:08:00Z"}, {"corporation_id": 1000180, "record_id": 44246273, "start_date": "2017-02-10T21:29:00Z"}, {"corporation_id": 1000006, "record_id": 44246259, "start_date": "2017-02-10T21:27:00Z"}, {"corporation_id": 98250486, "record_id": 44246225, "start_date": "2017-02-10T21:22:00Z"}, {"corporation_id": 1000167, "record_id": 43969421, "start_date": "2017-01-14T01:42:00Z"}]