[{"corporation_id": 98330748, "record_id": 50535674, "start_date": "2019-08-13T13:46:00Z"}, {"corporation_id": 1000066, "record_id": 50535400, "start_date": "2019-08-13T12:48:00Z"}, {"corporation_id": 1081142661, "record_id": 48265226, "start_date": "2018-08-20T21:12:00Z"}, {"corporation_id": 98421092, "record_id": 48179574, "start_date": "2018-08-08T21:13:00Z"}, {"corporation_id": 1000066, "record_id": 48162323, "start_date": "2018-08-06T12:52:00Z"}, {"corporation_id": 1554569661, "record_id": 46561688, "start_date": "2017-12-20T20:22:00Z"}, {"corporation_id": 98357569, "record_id": 46313769, "start_date": "2017-11-19T11:36:00Z"}, {"corporation_id": 1000077, "record_id": 45923985, "start_date": "2017-09-26T18:51:00Z"}]