[{"corporation_id": 1000165, "record_id": 55210953, "start_date": "2021-03-03T06:05:00Z"}, {"corporation_id": 98363074, "record_id": 54102283, "start_date": "2020-10-15T23:28:00Z"}, {"corporation_id": 98654819, "record_id": 54102233, "start_date": "2020-10-15T23:20:00Z"}, {"corporation_id": 1000066, "record_id": 53024363, "start_date": "2020-06-14T09:32:00Z"}, {"corporation_id": 98606027, "record_id": 52821496, "start_date": "2020-05-20T03:14:00Z"}, {"corporation_id": 1000066, "record_id": 52821091, "start_date": "2020-05-20T01:49:00Z"}, {"corporation_id": 98641367, "is_deleted": true, "record_id": 52654203, "start_date": "2020-05-05T03:59:00Z"}, {"corporation_id": 1000066, "record_id": 52654186, "start_date": "2020-05-05T03:57:00Z"}, {"corporation_id": 98606027, "record_id": 50873689, "start_date": "2019-10-13T02:21:00Z"}, {"corporation_id": 1000165, "record_id": 50565885, "start_date": "2019-08-18T06:41:00Z"}]