[{"corporation_id": 98491666, "record_id": 53760372, "start_date": "2020-09-02T10:03:00Z"}, {"corporation_id": 1000107, "record_id": 53760366, "start_date": "2020-09-02T10:02:00Z"}, {"corporation_id": 98562176, "record_id": 51324296, "start_date": "2019-12-10T22:32:00Z"}, {"corporation_id": 1000107, "record_id": 51324293, "start_date": "2019-12-10T22:31:00Z"}, {"corporation_id": 98598006, "is_deleted": true, "record_id": 50532265, "start_date": "2019-08-12T22:27:00Z"}, {"corporation_id": 1000107, "record_id": 50532261, "start_date": "2019-08-12T22:27:00Z"}, {"corporation_id": 98493578, "record_id": 49740003, "start_date": "2019-04-20T05:21:00Z"}, {"corporation_id": 1000168, "record_id": 49734027, "start_date": "2019-04-19T11:29:00Z"}]