[{"corporation_id": 724997872, "record_id": 54096908, "start_date": "2020-10-15T08:05:00Z"}, {"corporation_id": 1000046, "record_id": 53902118, "start_date": "2020-09-19T19:17:00Z"}, {"corporation_id": 724997872, "record_id": 53118290, "start_date": "2020-06-26T08:20:00Z"}, {"corporation_id": 1000046, "record_id": 53065070, "start_date": "2020-06-19T18:38:00Z"}, {"corporation_id": 724997872, "record_id": 52736998, "start_date": "2020-05-11T06:28:00Z"}, {"corporation_id": 1000046, "record_id": 52726432, "start_date": "2020-05-10T09:26:00Z"}, {"corporation_id": 98316453, "record_id": 52716821, "start_date": "2020-05-09T14:18:00Z"}, {"corporation_id": 1000046, "record_id": 52713619, "start_date": "2020-05-09T07:31:00Z"}, {"corporation_id": 98383539, "record_id": 52545540, "start_date": "2020-04-25T14:51:00Z"}, {"corporation_id": 1000046, "record_id": 52538586, "start_date": "2020-04-24T22:39:00Z"}, {"corporation_id": 1000182, "record_id": 52535418, "start_date": "2020-04-24T16:53:00Z"}, {"corporation_id": 1000046, "record_id": 52535413, "start_date": "2020-04-24T16:53:00Z"}, {"corporation_id": 98319564, "record_id": 52533843, "start_date": "2020-04-24T14:00:00Z"}, {"corporation_id": 1000046, "record_id": 52504249, "start_date": "2020-04-21T21:05:00Z"}, {"corporation_id": 98632357, "record_id": 52501007, "start_date": "2020-04-21T15:53:00Z"}, {"corporation_id": 1000172, "record_id": 52465210, "start_date": "2020-04-18T15:36:00Z"}]