[{"corporation_id": 1000046, "record_id": 49246110, "start_date": "2019-01-28T14:34:00Z"}, {"corporation_id": 98444361, "record_id": 47716743, "start_date": "2018-06-01T14:08:00Z"}, {"corporation_id": 1000046, "record_id": 44711712, "start_date": "2017-04-06T22:17:00Z"}, {"corporation_id": 98444361, "record_id": 43507170, "start_date": "2016-12-08T20:17:00Z"}, {"corporation_id": 1498436427, "record_id": 43367777, "start_date": "2016-11-30T00:35:00Z"}, {"corporation_id": 98012663, "record_id": 38005466, "start_date": "2015-05-04T11:36:00Z"}, {"corporation_id": 98143022, "record_id": 32972458, "start_date": "2014-05-22T05:28:00Z"}, {"corporation_id": 1818665957, "record_id": 20182818, "start_date": "2012-07-07T00:58:00Z"}, {"corporation_id": 1000046, "record_id": 19971409, "start_date": "2012-06-10T19:01:00Z"}, {"corporation_id": 98045646, "record_id": 17283920, "start_date": "2011-07-04T20:38:00Z"}, {"corporation_id": 1818665957, "record_id": 15469950, "start_date": "2010-12-07T19:33:00Z"}, {"corporation_id": 638247660, "record_id": 1072165, "start_date": "2009-05-10T09:37:00Z"}, {"corporation_id": 1818665957, "record_id": 1072164, "start_date": "2008-09-12T18:26:00Z"}, {"corporation_id": 1000046, "record_id": 1072163, "start_date": "2008-09-12T09:05:00Z"}, {"corporation_id": 356997754, "is_deleted": true, "record_id": 1072162, "start_date": "2008-05-30T14:49:00Z"}, {"corporation_id": 1000046, "record_id": 1072161, "start_date": "2008-05-25T17:26:00Z"}, {"corporation_id": 1942766150, "record_id": 1072160, "start_date": "2008-05-17T18:11:00Z"}, {"corporation_id": 1000046, "record_id": 1072159, "start_date": "2008-05-16T23:25:00Z"}, {"corporation_id": 414884517, "record_id": 1072158, "start_date": "2008-04-28T18:56:00Z"}, {"corporation_id": 1000046, "record_id": 1072157, "start_date": "2008-03-25T12:44:00Z"}, {"corporation_id": 749147334, "record_id": 1072156, "start_date": "2007-07-05T21:40:00Z"}, {"corporation_id": 414884517, "record_id": 1072155, "start_date": "2007-06-27T07:48:00Z"}, {"corporation_id": 1000046, "record_id": 1072154, "start_date": "2007-04-13T22:14:00Z"}, {"corporation_id": 423229765, "record_id": 1072153, "start_date": "2006-05-24T20:15:00Z"}, {"corporation_id": 134490366, "is_deleted": true, "record_id": 1072152, "start_date": "2006-01-09T15:28:00Z"}, {"corporation_id": 1000046, "record_id": 1072151, "start_date": "2006-01-09T15:24:00Z"}, {"corporation_id": 842313458, "is_deleted": true, "record_id": 1072150, "start_date": "2005-10-10T17:04:00Z"}, {"corporation_id": 1000046, "record_id": 1072149, "start_date": "2005-10-10T17:01:00Z"}, {"corporation_id": 134490366, "is_deleted": true, "record_id": 1072148, "start_date": "2005-07-29T17:07:00Z"}, {"corporation_id": 1000170, "record_id": 1072147, "start_date": "2005-06-13T01:49:00Z"}]