[{"corporation_id": 98556964, "record_id": 50246031, "start_date": "2019-07-03T20:16:00Z"}, {"corporation_id": 1000046, "record_id": 48718084, "start_date": "2018-11-04T11:06:00Z"}, {"corporation_id": 98532165, "record_id": 48208239, "start_date": "2018-08-12T18:20:00Z"}, {"corporation_id": 98457406, "record_id": 45365021, "start_date": "2017-07-02T12:02:00Z"}, {"corporation_id": 98146876, "record_id": 43926670, "start_date": "2017-01-09T15:09:00Z"}, {"corporation_id": 98467712, "record_id": 42925587, "start_date": "2016-10-27T18:19:00Z"}, {"corporation_id": 98457406, "record_id": 41978330, "start_date": "2016-05-14T14:53:00Z"}, {"corporation_id": 98356785, "record_id": 41101460, "start_date": "2016-02-14T15:04:00Z"}, {"corporation_id": 1000046, "record_id": 36252647, "start_date": "2014-12-13T11:55:00Z"}, {"corporation_id": 1317517961, "record_id": 35681217, "start_date": "2014-10-31T11:55:00Z"}, {"corporation_id": 98162180, "record_id": 35453399, "start_date": "2014-10-13T18:10:00Z"}, {"corporation_id": 939175599, "record_id": 31372438, "start_date": "2014-02-24T23:31:00Z"}, {"corporation_id": 1000046, "record_id": 29374369, "start_date": "2013-11-18T15:27:00Z"}, {"corporation_id": 897832479, "record_id": 26297622, "start_date": "2013-06-19T13:35:00Z"}, {"corporation_id": 98140883, "record_id": 24722852, "start_date": "2013-04-15T16:18:00Z"}, {"corporation_id": 98114942, "record_id": 21016869, "start_date": "2012-10-28T12:52:00Z"}, {"corporation_id": 1000046, "record_id": 20604216, "start_date": "2012-08-30T21:59:00Z"}, {"corporation_id": 98080699, "is_deleted": true, "record_id": 19212610, "start_date": "2012-03-16T14:37:00Z"}, {"corporation_id": 98072270, "is_deleted": true, "record_id": 18223711, "start_date": "2011-11-05T14:50:00Z"}, {"corporation_id": 98064426, "record_id": 17882740, "start_date": "2011-09-17T18:00:00Z"}, {"corporation_id": 98023835, "is_deleted": true, "record_id": 16655577, "start_date": "2011-04-23T21:02:00Z"}, {"corporation_id": 98019833, "record_id": 16026148, "start_date": "2011-02-06T21:17:00Z"}, {"corporation_id": 1000046, "record_id": 16025999, "start_date": "2011-02-06T21:06:00Z"}, {"corporation_id": 1050207992, "record_id": 15496869, "start_date": "2010-12-11T14:38:00Z"}, {"corporation_id": 1411055285, "record_id": 14906728, "start_date": "2010-09-25T14:20:00Z"}, {"corporation_id": 1000046, "record_id": 14906719, "start_date": "2010-09-25T14:18:00Z"}, {"corporation_id": 1624325839, "is_deleted": true, "record_id": 14532607, "start_date": "2010-08-08T22:55:00Z"}, {"corporation_id": 1019733022, "record_id": 14521430, "start_date": "2010-08-07T14:35:00Z"}, {"corporation_id": 277267844, "record_id": 13164603, "start_date": "2010-03-07T14:24:00Z"}, {"corporation_id": 346550330, "record_id": 13148812, "start_date": "2010-03-05T21:02:00Z"}, {"corporation_id": 1768658230, "is_deleted": true, "record_id": 13007214, "start_date": "2010-02-18T21:08:00Z"}, {"corporation_id": 1000046, "record_id": 13007177, "start_date": "2010-02-18T21:04:00Z"}, {"corporation_id": 1005050246, "is_deleted": true, "record_id": 12817338, "start_date": "2010-01-30T17:20:00Z"}, {"corporation_id": 1000046, "record_id": 12341500, "start_date": "2009-12-14T19:13:00Z"}, {"corporation_id": 239536795, "record_id": 12165070, "start_date": "2009-11-27T19:45:00Z"}, {"corporation_id": 547406787, "record_id": 10877869, "start_date": "2009-07-04T13:02:00Z"}, {"corporation_id": 1000046, "record_id": 10869998, "start_date": "2009-07-03T17:05:00Z"}, {"corporation_id": 547406787, "record_id": 1848398, "start_date": "2008-12-23T21:49:00Z"}, {"corporation_id": 1000046, "record_id": 1848397, "start_date": "2008-12-20T17:48:00Z"}, {"corporation_id": 1561103801, "record_id": 1848396, "start_date": "2008-12-20T16:15:00Z"}, {"corporation_id": 1000046, "record_id": 1848395, "start_date": "2008-12-16T04:53:00Z"}, {"corporation_id": 1433245646, "record_id": 1848394, "start_date": "2008-11-04T18:58:00Z"}, {"corporation_id": 1000046, "record_id": 1848393, "start_date": "2008-11-04T15:46:00Z"}, {"corporation_id": 911273305, "record_id": 1848392, "start_date": "2008-11-01T22:30:00Z"}, {"corporation_id": 1000046, "record_id": 1848391, "start_date": "2008-11-01T19:44:00Z"}, {"corporation_id": 109556861, "record_id": 1848390, "start_date": "2008-10-20T22:11:00Z"}, {"corporation_id": 1000046, "record_id": 1848389, "start_date": "2008-10-16T19:56:00Z"}, {"corporation_id": 1000182, "record_id": 1848388, "start_date": "2008-10-16T14:20:00Z"}, {"corporation_id": 1000046, "record_id": 1848387, "start_date": "2008-10-16T13:09:00Z"}, {"corporation_id": 1403414001, "record_id": 1848386, "start_date": "2008-08-19T21:29:00Z"}, {"corporation_id": 1000170, "record_id": 1848385, "start_date": "2008-08-18T15:06:00Z"}]