[{"corporation_id": 98252033, "record_id": 41046464, "start_date": "2016-02-08T19:00:00Z"}, {"corporation_id": 98007161, "record_id": 23243380, "start_date": "2013-02-08T13:50:00Z"}, {"corporation_id": 1021729675, "record_id": 15668870, "start_date": "2010-12-31T15:15:00Z"}, {"corporation_id": 1521760938, "is_deleted": true, "record_id": 2349731, "start_date": "2009-05-22T20:53:00Z"}, {"corporation_id": 1882201104, "is_deleted": true, "record_id": 2349730, "start_date": "2008-08-31T19:14:00Z"}, {"corporation_id": 1000114, "record_id": 2349729, "start_date": "2008-06-30T18:59:00Z"}, {"corporation_id": 1359866886, "record_id": 2349728, "start_date": "2008-04-05T17:50:00Z"}, {"corporation_id": 1000169, "record_id": 2349727, "start_date": "2008-03-26T13:52:00Z"}]