[{"corporation_id": 98546057, "record_id": 48096050, "start_date": "2018-07-28T11:30:00Z"}, {"corporation_id": 1000060, "record_id": 47954901, "start_date": "2018-07-06T21:01:00Z"}, {"corporation_id": 98519717, "record_id": 47318241, "start_date": "2018-04-05T20:24:00Z"}, {"corporation_id": 1000060, "record_id": 42418978, "start_date": "2016-07-24T16:01:00Z"}, {"corporation_id": 98432283, "record_id": 42238267, "start_date": "2016-06-17T21:38:00Z"}, {"corporation_id": 155144834, "record_id": 40080644, "start_date": "2015-11-12T10:28:00Z"}, {"corporation_id": 1000060, "record_id": 40072072, "start_date": "2015-11-11T13:00:00Z"}, {"corporation_id": 98425870, "is_deleted": true, "record_id": 39971227, "start_date": "2015-11-01T20:34:00Z"}, {"corporation_id": 98261514, "record_id": 39697951, "start_date": "2015-10-07T02:26:00Z"}, {"corporation_id": 1000060, "record_id": 39548373, "start_date": "2015-09-23T13:36:00Z"}, {"corporation_id": 148873883, "record_id": 37817602, "start_date": "2015-04-16T18:52:00Z"}, {"corporation_id": 1000060, "record_id": 37732687, "start_date": "2015-04-09T11:58:00Z"}, {"corporation_id": 98277387, "record_id": 32750304, "start_date": "2014-05-10T13:51:00Z"}, {"corporation_id": 1000060, "record_id": 32750267, "start_date": "2014-05-10T13:50:00Z"}, {"corporation_id": 98307645, "is_deleted": true, "record_id": 32313593, "start_date": "2014-04-16T16:22:00Z"}, {"corporation_id": 1000060, "record_id": 32232704, "start_date": "2014-04-12T09:03:00Z"}, {"corporation_id": 98301330, "is_deleted": true, "record_id": 32004019, "start_date": "2014-03-30T13:34:00Z"}, {"corporation_id": 1000060, "record_id": 31956781, "start_date": "2014-03-28T02:38:00Z"}, {"corporation_id": 98057188, "record_id": 31625794, "start_date": "2014-03-09T19:08:00Z"}, {"corporation_id": 1000060, "record_id": 31129728, "start_date": "2014-02-13T18:54:00Z"}, {"corporation_id": 98131886, "record_id": 30058835, "start_date": "2013-12-23T12:05:00Z"}, {"corporation_id": 1000060, "record_id": 30015869, "start_date": "2013-12-21T14:24:00Z"}, {"corporation_id": 1551432775, "is_deleted": true, "record_id": 29025396, "start_date": "2013-10-29T20:57:00Z"}, {"corporation_id": 1000060, "record_id": 29000244, "start_date": "2013-10-28T15:43:00Z"}, {"corporation_id": 98017240, "record_id": 28381686, "start_date": "2013-09-24T10:01:00Z"}, {"corporation_id": 1000060, "record_id": 28298863, "start_date": "2013-09-19T14:33:00Z"}, {"corporation_id": 98136169, "is_deleted": true, "record_id": 25401861, "start_date": "2013-05-20T13:42:00Z"}, {"corporation_id": 1000181, "record_id": 25368201, "start_date": "2013-05-19T17:31:00Z"}, {"corporation_id": 1000060, "record_id": 25366121, "start_date": "2013-05-19T16:41:00Z"}, {"corporation_id": 624410653, "record_id": 25136637, "start_date": "2013-05-11T22:13:00Z"}, {"corporation_id": 1000060, "record_id": 25029312, "start_date": "2013-05-05T13:46:00Z"}, {"corporation_id": 98196852, "is_deleted": true, "record_id": 24898989, "start_date": "2013-04-27T22:22:00Z"}, {"corporation_id": 1000060, "record_id": 24898936, "start_date": "2013-04-27T22:19:00Z"}, {"corporation_id": 98136169, "is_deleted": true, "record_id": 23598210, "start_date": "2013-02-17T22:49:00Z"}, {"corporation_id": 1000060, "record_id": 23593474, "start_date": "2013-02-17T20:46:00Z"}, {"corporation_id": 98131886, "record_id": 23480518, "start_date": "2013-02-14T20:48:00Z"}, {"corporation_id": 1000060, "record_id": 23416250, "start_date": "2013-02-12T18:37:00Z"}, {"corporation_id": 494556657, "is_deleted": true, "record_id": 13707513, "start_date": "2010-05-10T18:58:00Z"}, {"corporation_id": 1000060, "record_id": 13707444, "start_date": "2010-05-10T18:50:00Z"}, {"corporation_id": 1132466394, "record_id": 13235558, "start_date": "2010-03-15T18:29:00Z"}, {"corporation_id": 1000060, "record_id": 13215119, "start_date": "2010-03-13T12:55:00Z"}, {"corporation_id": 2052569328, "record_id": 13074031, "start_date": "2010-02-25T18:08:00Z"}, {"corporation_id": 494556657, "is_deleted": true, "record_id": 12310254, "start_date": "2009-12-11T22:09:00Z"}, {"corporation_id": 1000060, "record_id": 12310189, "start_date": "2009-12-11T22:04:00Z"}, {"corporation_id": 308742228, "record_id": 12259148, "start_date": "2009-12-06T20:40:00Z"}, {"corporation_id": 1000060, "record_id": 11582414, "start_date": "2009-09-19T10:45:00Z"}, {"corporation_id": 684279878, "record_id": 2405076, "start_date": "2009-01-12T18:59:00Z"}, {"corporation_id": 1000171, "record_id": 2405075, "start_date": "2009-01-12T13:35:00Z"}]