[{"corporation_id": 98169165, "record_id": 48400529, "start_date": "2018-09-10T21:54:00Z"}, {"corporation_id": 98223798, "record_id": 45665174, "start_date": "2017-08-20T02:17:00Z"}, {"corporation_id": 1000006, "record_id": 45613935, "start_date": "2017-08-12T09:56:00Z"}, {"corporation_id": 98330748, "record_id": 45423643, "start_date": "2017-07-12T04:43:00Z"}, {"corporation_id": 98223798, "record_id": 42365070, "start_date": "2016-07-12T06:15:00Z"}, {"corporation_id": 1000006, "record_id": 42365067, "start_date": "2016-07-12T06:15:00Z"}, {"corporation_id": 98440615, "is_deleted": true, "record_id": 42353723, "start_date": "2016-07-09T23:26:00Z"}, {"corporation_id": 1000006, "record_id": 42353713, "start_date": "2016-07-09T23:24:00Z"}, {"corporation_id": 98223798, "record_id": 42324589, "start_date": "2016-07-04T07:31:00Z"}, {"corporation_id": 1000006, "record_id": 42324582, "start_date": "2016-07-04T07:27:00Z"}, {"corporation_id": 98031737, "record_id": 37479241, "start_date": "2015-03-20T18:27:00Z"}, {"corporation_id": 1000006, "record_id": 37473563, "start_date": "2015-03-20T03:54:00Z"}, {"corporation_id": 98223798, "record_id": 35716074, "start_date": "2014-11-02T17:07:00Z"}, {"corporation_id": 98031737, "record_id": 33072436, "start_date": "2014-05-26T19:28:00Z"}, {"corporation_id": 1000006, "record_id": 32840167, "start_date": "2014-05-15T04:16:00Z"}, {"corporation_id": 1465050528, "record_id": 32780594, "start_date": "2014-05-11T19:05:00Z"}, {"corporation_id": 1000006, "record_id": 31908278, "start_date": "2014-03-25T03:55:00Z"}, {"corporation_id": 98031737, "record_id": 31632757, "start_date": "2014-03-10T01:45:00Z"}, {"corporation_id": 1102941417, "is_deleted": true, "record_id": 31430946, "start_date": "2014-02-28T03:02:00Z"}, {"corporation_id": 309807724, "record_id": 3764134, "start_date": "2007-03-21T01:46:00Z"}, {"corporation_id": 1000006, "record_id": 3764133, "start_date": "2007-03-20T10:54:00Z"}, {"corporation_id": 876338812, "record_id": 3764132, "start_date": "2006-04-07T00:42:00Z"}, {"corporation_id": 1000006, "record_id": 3764131, "start_date": "2006-03-27T01:22:00Z"}, {"corporation_id": 876338812, "record_id": 3764130, "start_date": "2006-01-21T18:07:00Z"}, {"corporation_id": 1000167, "record_id": 3764129, "start_date": "2006-01-21T06:20:00Z"}]