[{"corporation_id": 98451632, "record_id": 55217423, "start_date": "2021-03-04T01:46:00Z"}, {"corporation_id": 1000167, "record_id": 55217416, "start_date": "2021-03-04T01:44:00Z"}, {"corporation_id": 971474490, "record_id": 50504684, "start_date": "2019-08-09T03:17:00Z"}, {"corporation_id": 1000006, "record_id": 50497818, "start_date": "2019-08-08T03:06:00Z"}, {"corporation_id": 98451632, "record_id": 46973976, "start_date": "2018-02-14T03:47:00Z"}, {"corporation_id": 1000006, "record_id": 46973971, "start_date": "2018-02-14T03:45:00Z"}, {"corporation_id": 709221692, "record_id": 41828881, "start_date": "2016-04-30T19:14:00Z"}, {"corporation_id": 1000006, "record_id": 41826789, "start_date": "2016-04-30T14:33:00Z"}, {"corporation_id": 98415604, "record_id": 39245023, "start_date": "2015-08-28T15:51:00Z"}, {"corporation_id": 1000006, "record_id": 37225767, "start_date": "2015-02-26T10:20:00Z"}, {"corporation_id": 98040755, "record_id": 36800064, "start_date": "2015-01-21T01:44:00Z"}, {"corporation_id": 1000006, "record_id": 36772965, "start_date": "2015-01-18T21:31:00Z"}, {"corporation_id": 719225339, "record_id": 36088728, "start_date": "2014-12-01T00:20:00Z"}, {"corporation_id": 1000006, "record_id": 35963509, "start_date": "2014-11-22T22:32:00Z"}, {"corporation_id": 98213204, "record_id": 26010562, "start_date": "2013-06-09T03:36:00Z"}, {"corporation_id": 1000006, "record_id": 25681271, "start_date": "2013-05-29T03:43:00Z"}, {"corporation_id": 98187195, "record_id": 25349208, "start_date": "2013-05-19T06:51:00Z"}, {"corporation_id": 98200506, "is_deleted": true, "record_id": 25118740, "start_date": "2013-05-10T23:43:00Z"}, {"corporation_id": 1000006, "record_id": 16838342, "start_date": "2011-05-16T22:55:00Z"}, {"corporation_id": 98019136, "record_id": 16577381, "start_date": "2011-04-13T23:20:00Z"}, {"corporation_id": 1000006, "record_id": 16546058, "start_date": "2011-04-10T06:57:00Z"}, {"corporation_id": 1576171750, "record_id": 16232535, "start_date": "2011-03-02T03:06:00Z"}, {"corporation_id": 1000006, "record_id": 15389548, "start_date": "2010-11-28T00:39:00Z"}, {"corporation_id": 1053771069, "record_id": 14076454, "start_date": "2010-06-17T23:12:00Z"}, {"corporation_id": 1000006, "record_id": 14070708, "start_date": "2010-06-17T08:47:00Z"}, {"corporation_id": 1675156823, "record_id": 13905707, "start_date": "2010-06-01T05:14:00Z"}, {"corporation_id": 1169948630, "record_id": 13616714, "start_date": "2010-04-30T06:07:00Z"}, {"corporation_id": 1000006, "record_id": 13589799, "start_date": "2010-04-26T21:51:00Z"}, {"corporation_id": 1673057478, "is_deleted": true, "record_id": 12844161, "start_date": "2010-02-02T06:54:00Z"}, {"corporation_id": 1095222071, "record_id": 12723351, "start_date": "2010-01-20T20:19:00Z"}, {"corporation_id": 1000006, "record_id": 12693450, "start_date": "2010-01-17T20:22:00Z"}, {"corporation_id": 430577669, "record_id": 10797573, "start_date": "2009-06-25T02:46:00Z"}, {"corporation_id": 1000006, "record_id": 10797111, "start_date": "2009-06-25T01:17:00Z"}, {"corporation_id": 1586619781, "record_id": 5564441, "start_date": "2009-02-23T02:17:00Z"}, {"corporation_id": 1000006, "record_id": 5564440, "start_date": "2009-02-23T01:32:00Z"}, {"corporation_id": 566825158, "record_id": 5564439, "start_date": "2009-01-28T06:45:00Z"}, {"corporation_id": 1000006, "record_id": 5564438, "start_date": "2009-01-28T06:40:00Z"}, {"corporation_id": 1673057478, "is_deleted": true, "record_id": 5564437, "start_date": "2008-10-30T18:11:00Z"}, {"corporation_id": 1000006, "record_id": 5564436, "start_date": "2008-10-30T09:49:00Z"}, {"corporation_id": 814878810, "record_id": 5564435, "start_date": "2008-10-25T10:45:00Z"}, {"corporation_id": 1000180, "record_id": 5564434, "start_date": "2008-10-25T09:06:00Z"}, {"corporation_id": 1000006, "record_id": 5564433, "start_date": "2008-10-25T06:19:00Z"}, {"corporation_id": 1000180, "record_id": 5564432, "start_date": "2008-10-24T07:30:00Z"}, {"corporation_id": 1000006, "record_id": 5564431, "start_date": "2008-09-17T21:39:00Z"}, {"corporation_id": 164893220, "record_id": 5564430, "start_date": "2008-04-11T05:58:00Z"}, {"corporation_id": 1000006, "record_id": 5564429, "start_date": "2008-04-11T05:31:00Z"}, {"corporation_id": 1201460556, "record_id": 5564428, "start_date": "2008-03-18T06:43:00Z"}, {"corporation_id": 1412993694, "record_id": 5564427, "start_date": "2007-09-09T02:30:00Z"}, {"corporation_id": 1000006, "record_id": 5564426, "start_date": "2007-08-29T17:11:00Z"}, {"corporation_id": 1412993694, "record_id": 5564425, "start_date": "2007-06-14T09:34:00Z"}, {"corporation_id": 113931003, "record_id": 5564424, "start_date": "2007-05-29T13:16:00Z"}, {"corporation_id": 599780357, "is_deleted": true, "record_id": 5564423, "start_date": "2007-03-13T09:34:00Z"}, {"corporation_id": 1260421913, "record_id": 5564422, "start_date": "2007-01-17T23:25:00Z"}, {"corporation_id": 1000167, "record_id": 5564421, "start_date": "2007-01-14T04:23:00Z"}]