[{"corporation_id": 98370861, "record_id": 52009222, "start_date": "2020-03-06T23:37:00Z"}, {"corporation_id": 264508111, "record_id": 49620307, "start_date": "2019-03-31T19:01:00Z"}, {"corporation_id": 1000049, "record_id": 49081936, "start_date": "2019-01-01T20:54:00Z"}, {"corporation_id": 98422578, "record_id": 47404156, "start_date": "2018-04-18T03:02:00Z"}, {"corporation_id": 1000049, "record_id": 47404051, "start_date": "2018-04-18T02:40:00Z"}, {"corporation_id": 98518006, "is_deleted": true, "record_id": 45325637, "start_date": "2017-06-25T23:06:00Z"}, {"corporation_id": 1000049, "record_id": 45325183, "start_date": "2017-06-25T21:29:00Z"}, {"corporation_id": 98098857, "record_id": 19106878, "start_date": "2012-03-03T02:34:00Z"}, {"corporation_id": 1000049, "record_id": 19102343, "start_date": "2012-03-02T15:21:00Z"}, {"corporation_id": 98098736, "is_deleted": true, "record_id": 19102329, "start_date": "2012-03-02T15:18:00Z"}, {"corporation_id": 1000049, "record_id": 19098539, "start_date": "2012-03-02T00:56:00Z"}, {"corporation_id": 98088437, "record_id": 18967333, "start_date": "2012-02-14T19:06:00Z"}, {"corporation_id": 1000049, "record_id": 18966049, "start_date": "2012-02-14T15:48:00Z"}, {"corporation_id": 98069512, "record_id": 18953488, "start_date": "2012-02-12T23:34:00Z"}, {"corporation_id": 1000049, "record_id": 18953405, "start_date": "2012-02-12T23:23:00Z"}, {"corporation_id": 98088437, "record_id": 18875376, "start_date": "2012-02-03T01:41:00Z"}, {"corporation_id": 1000049, "record_id": 17593372, "start_date": "2011-08-09T03:27:00Z"}, {"corporation_id": 1662915388, "record_id": 16555984, "start_date": "2011-04-11T08:47:00Z"}, {"corporation_id": 1000172, "record_id": 16520428, "start_date": "2011-04-07T04:31:00Z"}]