[{"corporation_id": 1000009, "record_id": 47883027, "start_date": "2018-06-24T21:48:00Z"}, {"corporation_id": 98288233, "record_id": 32160029, "start_date": "2014-04-07T23:06:00Z"}, {"corporation_id": 1000009, "record_id": 32141928, "start_date": "2014-04-06T22:04:00Z"}, {"corporation_id": 98252033, "record_id": 28586380, "start_date": "2013-10-06T15:23:00Z"}, {"corporation_id": 98189116, "is_deleted": true, "record_id": 26565457, "start_date": "2013-06-30T11:28:00Z"}, {"corporation_id": 1000009, "record_id": 24510102, "start_date": "2013-04-01T17:53:00Z"}, {"corporation_id": 1119499077, "record_id": 21060103, "start_date": "2012-11-03T17:37:00Z"}, {"corporation_id": 1000009, "record_id": 21052388, "start_date": "2012-11-02T16:34:00Z"}, {"corporation_id": 239536795, "record_id": 18482011, "start_date": "2011-12-12T09:07:00Z"}, {"corporation_id": 1000009, "record_id": 18447161, "start_date": "2011-12-08T07:20:00Z"}, {"corporation_id": 98015637, "is_deleted": true, "record_id": 16835816, "start_date": "2011-05-16T17:52:00Z"}, {"corporation_id": 1000045, "record_id": 16757733, "start_date": "2011-05-06T20:23:00Z"}]