[{"corporation_id": 98380820, "record_id": 54982129, "start_date": "2021-02-06T04:44:00Z"}, {"corporation_id": 1000115, "record_id": 54981118, "start_date": "2021-02-06T01:04:00Z"}, {"corporation_id": 98380820, "record_id": 54696718, "start_date": "2021-01-02T08:41:00Z"}, {"corporation_id": 1000115, "record_id": 54681008, "start_date": "2020-12-31T09:39:00Z"}, {"corporation_id": 98453960, "record_id": 54490904, "start_date": "2020-12-05T10:34:00Z"}, {"corporation_id": 1000107, "record_id": 54490902, "start_date": "2020-12-05T10:34:00Z"}, {"corporation_id": 98659806, "is_deleted": true, "record_id": 54037612, "start_date": "2020-10-07T14:14:00Z"}, {"corporation_id": 1000107, "record_id": 54037480, "start_date": "2020-10-07T13:48:00Z"}, {"corporation_id": 98434943, "record_id": 53680770, "start_date": "2020-08-25T02:54:00Z"}, {"corporation_id": 1000107, "record_id": 53680751, "start_date": "2020-08-25T02:51:00Z"}, {"corporation_id": 98558359, "is_deleted": true, "record_id": 47572037, "start_date": "2018-05-10T14:51:00Z"}, {"corporation_id": 1000107, "record_id": 47572036, "start_date": "2018-05-10T14:51:00Z"}, {"corporation_id": 98490682, "record_id": 43598850, "start_date": "2016-12-14T17:31:00Z"}, {"corporation_id": 1000107, "record_id": 43598830, "start_date": "2016-12-14T17:30:00Z"}, {"corporation_id": 98490679, "is_deleted": true, "record_id": 43598685, "start_date": "2016-12-14T17:18:00Z"}, {"corporation_id": 1000107, "record_id": 43598428, "start_date": "2016-12-14T16:59:00Z"}, {"corporation_id": 98085333, "record_id": 18586768, "start_date": "2011-12-26T17:27:00Z"}, {"corporation_id": 1000115, "record_id": 17214202, "start_date": "2011-06-27T14:36:00Z"}]