[{"corporation_id": 98375813, "record_id": 52569920, "start_date": "2020-04-27T15:17:00Z"}, {"corporation_id": 98096652, "record_id": 52330039, "start_date": "2020-04-07T15:52:00Z"}, {"corporation_id": 1000107, "record_id": 48126652, "start_date": "2018-08-01T17:22:00Z"}, {"corporation_id": 200097278, "record_id": 39884172, "start_date": "2015-10-24T22:39:00Z"}, {"corporation_id": 1000107, "record_id": 38712526, "start_date": "2015-07-15T04:25:00Z"}, {"corporation_id": 98290394, "record_id": 38358097, "start_date": "2015-06-09T12:45:00Z"}, {"corporation_id": 98096652, "record_id": 36198093, "start_date": "2014-12-09T21:48:00Z"}, {"corporation_id": 1821559436, "record_id": 35281492, "start_date": "2014-09-30T18:46:00Z"}, {"corporation_id": 98096652, "record_id": 34614033, "start_date": "2014-08-18T16:59:00Z"}, {"corporation_id": 200097278, "record_id": 34244084, "start_date": "2014-07-29T18:19:00Z"}, {"corporation_id": 1000107, "record_id": 34244007, "start_date": "2014-07-29T18:17:00Z"}, {"corporation_id": 98096652, "record_id": 31858948, "start_date": "2014-03-22T19:52:00Z"}, {"corporation_id": 200097278, "record_id": 31368100, "start_date": "2014-02-24T19:22:00Z"}, {"corporation_id": 1000107, "record_id": 31368094, "start_date": "2014-02-24T19:22:00Z"}, {"corporation_id": 98275563, "record_id": 31068329, "start_date": "2014-02-10T18:49:00Z"}, {"corporation_id": 1000107, "record_id": 31067194, "start_date": "2014-02-10T17:48:00Z"}, {"corporation_id": 200097278, "record_id": 25169757, "start_date": "2013-05-13T18:56:00Z"}, {"corporation_id": 1000107, "record_id": 25167597, "start_date": "2013-05-13T16:36:00Z"}, {"corporation_id": 1831131676, "record_id": 24148793, "start_date": "2013-03-11T19:57:00Z"}, {"corporation_id": 1000107, "record_id": 24145591, "start_date": "2013-03-11T16:43:00Z"}, {"corporation_id": 200097278, "record_id": 18588722, "start_date": "2011-12-26T22:22:00Z"}, {"corporation_id": 1000115, "record_id": 18572959, "start_date": "2011-12-24T13:09:00Z"}]