[{"corporation_id": 98639571, "record_id": 54939718, "start_date": "2021-02-01T04:37:00Z"}, {"corporation_id": 1000044, "record_id": 54854113, "start_date": "2021-01-21T21:38:00Z"}, {"corporation_id": 98566768, "record_id": 54313166, "start_date": "2020-11-11T09:35:00Z"}, {"corporation_id": 1000006, "record_id": 54313158, "start_date": "2020-11-11T09:34:00Z"}, {"corporation_id": 98639571, "record_id": 52994170, "start_date": "2020-06-10T18:04:00Z"}, {"corporation_id": 1000006, "record_id": 52994169, "start_date": "2020-06-10T18:04:00Z"}, {"corporation_id": 98277256, "record_id": 51888811, "start_date": "2020-02-21T15:11:00Z"}, {"corporation_id": 1000006, "record_id": 49997764, "start_date": "2019-05-29T00:08:00Z"}, {"corporation_id": 98290394, "record_id": 47998344, "start_date": "2018-07-13T17:21:00Z"}, {"corporation_id": 1000006, "record_id": 47998243, "start_date": "2018-07-13T17:02:00Z"}, {"corporation_id": 98457503, "record_id": 45447013, "start_date": "2017-07-16T05:58:00Z"}, {"corporation_id": 98502812, "record_id": 45267285, "start_date": "2017-06-17T00:42:00Z"}, {"corporation_id": 1000006, "record_id": 45267284, "start_date": "2017-06-17T00:41:00Z"}, {"corporation_id": 98500662, "record_id": 44212242, "start_date": "2017-02-07T00:14:00Z"}, {"corporation_id": 1000006, "record_id": 44212174, "start_date": "2017-02-07T00:05:00Z"}, {"corporation_id": 98277256, "record_id": 44131122, "start_date": "2017-01-29T21:23:00Z"}, {"corporation_id": 1000006, "record_id": 44131119, "start_date": "2017-01-29T21:22:00Z"}, {"corporation_id": 98136895, "record_id": 42779197, "start_date": "2016-09-29T00:48:00Z"}, {"corporation_id": 1000006, "record_id": 42779196, "start_date": "2016-09-29T00:48:00Z"}, {"corporation_id": 98472952, "record_id": 42741656, "start_date": "2016-09-21T07:55:00Z"}, {"corporation_id": 98333438, "record_id": 42741548, "start_date": "2016-09-21T06:54:00Z"}, {"corporation_id": 1000006, "record_id": 42741547, "start_date": "2016-09-21T06:54:00Z"}, {"corporation_id": 98369801, "record_id": 42434623, "start_date": "2016-07-28T06:39:00Z"}, {"corporation_id": 1000006, "record_id": 41487723, "start_date": "2016-03-28T17:25:00Z"}, {"corporation_id": 98437473, "record_id": 41136885, "start_date": "2016-02-18T11:42:00Z"}, {"corporation_id": 98362183, "record_id": 41065355, "start_date": "2016-02-10T21:14:00Z"}, {"corporation_id": 1000006, "record_id": 41065285, "start_date": "2016-02-10T21:07:00Z"}, {"corporation_id": 624595551, "record_id": 40475069, "start_date": "2015-12-20T01:44:00Z"}, {"corporation_id": 1000006, "record_id": 40475058, "start_date": "2015-12-20T01:43:00Z"}, {"corporation_id": 1607489183, "record_id": 40128896, "start_date": "2015-11-17T00:30:00Z"}, {"corporation_id": 1000006, "record_id": 40125107, "start_date": "2015-11-16T17:12:00Z"}, {"corporation_id": 98427520, "record_id": 40061431, "start_date": "2015-11-10T05:33:00Z"}, {"corporation_id": 98415060, "record_id": 40061170, "start_date": "2015-11-10T04:38:00Z"}, {"corporation_id": 1000006, "record_id": 40061169, "start_date": "2015-11-10T04:38:00Z"}, {"corporation_id": 98427520, "record_id": 40035039, "start_date": "2015-11-07T22:17:00Z"}, {"corporation_id": 1000006, "record_id": 40005015, "start_date": "2015-11-05T03:08:00Z"}, {"corporation_id": 98297019, "record_id": 39565278, "start_date": "2015-09-25T04:25:00Z"}, {"corporation_id": 1000006, "record_id": 39565274, "start_date": "2015-09-25T04:24:00Z"}, {"corporation_id": 98277256, "record_id": 38649696, "start_date": "2015-07-09T09:43:00Z"}, {"corporation_id": 1000006, "record_id": 38649695, "start_date": "2015-07-09T09:43:00Z"}, {"corporation_id": 98377234, "record_id": 37112897, "start_date": "2015-02-16T03:15:00Z"}, {"corporation_id": 1000006, "record_id": 37112894, "start_date": "2015-02-16T03:14:00Z"}, {"corporation_id": 98161321, "record_id": 37112344, "start_date": "2015-02-16T01:53:00Z"}, {"corporation_id": 98377234, "record_id": 37112321, "start_date": "2015-02-16T01:50:00Z"}, {"corporation_id": 1000006, "record_id": 37112320, "start_date": "2015-02-16T01:50:00Z"}, {"corporation_id": 98161321, "record_id": 36810413, "start_date": "2015-01-22T00:01:00Z"}, {"corporation_id": 98277256, "record_id": 31838371, "start_date": "2014-03-21T21:05:00Z"}, {"corporation_id": 1000006, "record_id": 31838220, "start_date": "2014-03-21T20:56:00Z"}, {"corporation_id": 98232800, "record_id": 31374699, "start_date": "2014-02-25T02:07:00Z"}, {"corporation_id": 1000006, "record_id": 31374682, "start_date": "2014-02-25T02:06:00Z"}, {"corporation_id": 98277256, "record_id": 30461973, "start_date": "2014-01-14T03:43:00Z"}, {"corporation_id": 1000006, "record_id": 30461950, "start_date": "2014-01-14T03:42:00Z"}, {"corporation_id": 98136007, "record_id": 29648346, "start_date": "2013-12-01T03:46:00Z"}, {"corporation_id": 1000006, "record_id": 29648339, "start_date": "2013-12-01T03:46:00Z"}, {"corporation_id": 98232800, "record_id": 29282576, "start_date": "2013-11-13T20:12:00Z"}, {"corporation_id": 98152497, "is_deleted": true, "record_id": 28829606, "start_date": "2013-10-20T02:55:00Z"}, {"corporation_id": 1000006, "record_id": 28824823, "start_date": "2013-10-19T22:13:00Z"}, {"corporation_id": 98256780, "is_deleted": true, "record_id": 28818981, "start_date": "2013-10-19T17:23:00Z"}, {"corporation_id": 1000006, "record_id": 28818962, "start_date": "2013-10-19T17:22:00Z"}, {"corporation_id": 98152497, "is_deleted": true, "record_id": 28294209, "start_date": "2013-09-19T03:31:00Z"}, {"corporation_id": 1000006, "record_id": 28275602, "start_date": "2013-09-17T20:49:00Z"}, {"corporation_id": 98136007, "record_id": 28005622, "start_date": "2013-09-01T20:14:00Z"}, {"corporation_id": 98187522, "record_id": 27945909, "start_date": "2013-08-30T00:55:00Z"}, {"corporation_id": 1000006, "record_id": 27945897, "start_date": "2013-08-30T00:54:00Z"}, {"corporation_id": 98236670, "record_id": 27921085, "start_date": "2013-08-28T18:23:00Z"}, {"corporation_id": 1000006, "record_id": 27860826, "start_date": "2013-08-25T16:51:00Z"}, {"corporation_id": 98136007, "record_id": 27761818, "start_date": "2013-08-20T19:15:00Z"}, {"corporation_id": 1000006, "record_id": 27760421, "start_date": "2013-08-20T17:57:00Z"}, {"corporation_id": 98236716, "record_id": 27447264, "start_date": "2013-08-07T03:47:00Z"}, {"corporation_id": 1000006, "record_id": 27436763, "start_date": "2013-08-06T19:01:00Z"}, {"corporation_id": 98136007, "record_id": 26239712, "start_date": "2013-06-17T01:28:00Z"}, {"corporation_id": 1000006, "record_id": 25863047, "start_date": "2013-06-04T22:54:00Z"}, {"corporation_id": 98095634, "record_id": 23714091, "start_date": "2013-02-21T20:34:00Z"}, {"corporation_id": 1000006, "record_id": 23695916, "start_date": "2013-02-21T02:16:00Z"}, {"corporation_id": 98154872, "record_id": 21400190, "start_date": "2012-12-15T17:48:00Z"}, {"corporation_id": 1000006, "record_id": 21374732, "start_date": "2012-12-12T23:54:00Z"}, {"corporation_id": 98149142, "is_deleted": true, "record_id": 21259173, "start_date": "2012-12-01T18:58:00Z"}, {"corporation_id": 98095634, "record_id": 20582832, "start_date": "2012-08-27T18:46:00Z"}, {"corporation_id": 98129595, "is_deleted": true, "record_id": 20532234, "start_date": "2012-08-20T19:38:00Z"}, {"corporation_id": 634477289, "record_id": 20178270, "start_date": "2012-07-06T13:48:00Z"}, {"corporation_id": 1000006, "record_id": 20173480, "start_date": "2012-07-05T21:05:00Z"}, {"corporation_id": 98089717, "record_id": 19225152, "start_date": "2012-03-18T01:19:00Z"}, {"corporation_id": 1000044, "record_id": 19113240, "start_date": "2012-03-03T19:49:00Z"}]