[{"corporation_id": 98424696, "record_id": 42132637, "start_date": "2016-05-29T22:47:00Z"}, {"corporation_id": 98290394, "record_id": 39129282, "start_date": "2015-08-18T05:02:00Z"}, {"corporation_id": 1000046, "record_id": 38697417, "start_date": "2015-07-13T18:41:00Z"}, {"corporation_id": 98040755, "record_id": 36983759, "start_date": "2015-02-04T18:36:00Z"}, {"corporation_id": 1000046, "record_id": 36911266, "start_date": "2015-01-29T23:55:00Z"}, {"corporation_id": 98169165, "record_id": 31600167, "start_date": "2014-03-08T17:00:00Z"}, {"corporation_id": 1000046, "record_id": 31587730, "start_date": "2014-03-08T01:27:00Z"}, {"corporation_id": 98123960, "is_deleted": true, "record_id": 20149618, "start_date": "2012-07-02T21:01:00Z"}, {"corporation_id": 917701062, "record_id": 19641260, "start_date": "2012-05-03T14:00:00Z"}, {"corporation_id": 1000170, "record_id": 19590615, "start_date": "2012-04-27T23:33:00Z"}]