[{"corporation_id": 1000107, "record_id": 53913446, "start_date": "2020-09-21T01:49:00Z"}, {"corporation_id": 98330748, "record_id": 50210622, "start_date": "2019-06-28T21:42:00Z"}, {"corporation_id": 1000107, "record_id": 50210621, "start_date": "2019-06-28T21:42:00Z"}, {"corporation_id": 98605415, "record_id": 50173961, "start_date": "2019-06-22T17:17:00Z"}, {"corporation_id": 1000107, "record_id": 50173880, "start_date": "2019-06-22T17:01:00Z"}, {"corporation_id": 98588453, "record_id": 49767028, "start_date": "2019-04-24T00:26:00Z"}, {"corporation_id": 1000107, "record_id": 49766618, "start_date": "2019-04-23T22:37:00Z"}, {"corporation_id": 98585359, "is_deleted": true, "record_id": 49753365, "start_date": "2019-04-21T22:11:00Z"}, {"corporation_id": 1000107, "record_id": 49753356, "start_date": "2019-04-21T22:09:00Z"}, {"corporation_id": 98587223, "record_id": 49595171, "start_date": "2019-03-27T23:26:00Z"}, {"corporation_id": 1000107, "record_id": 49595159, "start_date": "2019-03-27T23:23:00Z"}, {"corporation_id": 98585110, "record_id": 49439902, "start_date": "2019-03-01T23:03:00Z"}, {"corporation_id": 1000107, "record_id": 37150000, "start_date": "2015-02-19T16:12:00Z"}, {"corporation_id": 1003546738, "record_id": 36745602, "start_date": "2015-01-17T03:02:00Z"}, {"corporation_id": 1000107, "record_id": 36132994, "start_date": "2014-12-04T22:24:00Z"}, {"corporation_id": 1003546738, "record_id": 34100365, "start_date": "2014-07-23T02:06:00Z"}, {"corporation_id": 1000107, "record_id": 34081147, "start_date": "2014-07-22T01:56:00Z"}, {"corporation_id": 98125159, "record_id": 31736283, "start_date": "2014-03-16T00:58:00Z"}, {"corporation_id": 98074735, "record_id": 31697707, "start_date": "2014-03-13T23:50:00Z"}, {"corporation_id": 1000107, "record_id": 31697697, "start_date": "2014-03-13T23:49:00Z"}, {"corporation_id": 98197556, "record_id": 25102022, "start_date": "2013-05-09T22:46:00Z"}, {"corporation_id": 98178536, "record_id": 24968370, "start_date": "2013-05-01T22:06:00Z"}, {"corporation_id": 1000107, "record_id": 24960633, "start_date": "2013-05-01T12:12:00Z"}, {"corporation_id": 98197556, "record_id": 24954374, "start_date": "2013-05-01T00:58:00Z"}, {"corporation_id": 98178536, "record_id": 23698816, "start_date": "2013-02-21T04:28:00Z"}, {"corporation_id": 1000107, "record_id": 23698569, "start_date": "2013-02-21T04:16:00Z"}, {"corporation_id": 98017771, "record_id": 21141410, "start_date": "2012-11-15T00:25:00Z"}, {"corporation_id": 1000107, "record_id": 21141408, "start_date": "2012-11-15T00:25:00Z"}, {"corporation_id": 98117973, "record_id": 19965447, "start_date": "2012-06-10T03:14:00Z"}, {"corporation_id": 98079238, "record_id": 19940709, "start_date": "2012-06-07T01:50:00Z"}, {"corporation_id": 1000169, "record_id": 19924250, "start_date": "2012-06-05T02:01:00Z"}]