[{"corporation_id": 1000006, "record_id": 49243590, "start_date": "2019-01-28T00:58:00Z"}, {"corporation_id": 98439551, "record_id": 41677151, "start_date": "2016-04-14T22:25:00Z"}, {"corporation_id": 1552312459, "record_id": 41575687, "start_date": "2016-04-05T03:30:00Z"}, {"corporation_id": 1000006, "record_id": 41524592, "start_date": "2016-03-31T23:49:00Z"}, {"corporation_id": 98198995, "record_id": 40185907, "start_date": "2015-11-23T01:03:00Z"}, {"corporation_id": 1000006, "record_id": 40167726, "start_date": "2015-11-21T15:43:00Z"}, {"corporation_id": 98290394, "record_id": 39077336, "start_date": "2015-08-14T03:52:00Z"}, {"corporation_id": 1000006, "record_id": 38618032, "start_date": "2015-07-06T03:06:00Z"}, {"corporation_id": 98290394, "record_id": 35444595, "start_date": "2014-10-12T23:58:00Z"}, {"corporation_id": 1000006, "record_id": 35439521, "start_date": "2014-10-12T18:00:00Z"}, {"corporation_id": 98287599, "record_id": 30933482, "start_date": "2014-02-05T01:40:00Z"}, {"corporation_id": 1000006, "record_id": 30845564, "start_date": "2014-02-01T21:06:00Z"}, {"corporation_id": 415564055, "record_id": 30346480, "start_date": "2014-01-07T14:19:00Z"}, {"corporation_id": 1000006, "record_id": 30288163, "start_date": "2014-01-04T13:29:00Z"}, {"corporation_id": 98114328, "record_id": 29987578, "start_date": "2013-12-20T01:55:00Z"}, {"corporation_id": 1000006, "record_id": 29986962, "start_date": "2013-12-20T01:04:00Z"}, {"corporation_id": 1699307293, "record_id": 28898284, "start_date": "2013-10-23T23:46:00Z"}, {"corporation_id": 917701062, "record_id": 23706503, "start_date": "2013-02-21T14:53:00Z"}, {"corporation_id": 1000044, "record_id": 22703072, "start_date": "2013-01-28T17:47:00Z"}]