[{"corporation_id": 98330748, "record_id": 51457120, "start_date": "2019-12-28T23:36:00Z"}, {"corporation_id": 1000009, "record_id": 51400507, "start_date": "2019-12-21T12:15:00Z"}, {"corporation_id": 98415266, "record_id": 50675455, "start_date": "2019-09-06T17:14:00Z"}, {"corporation_id": 98330748, "record_id": 49171403, "start_date": "2019-01-16T09:25:00Z"}, {"corporation_id": 1000009, "record_id": 45885916, "start_date": "2017-09-22T02:17:00Z"}, {"corporation_id": 351529526, "record_id": 41294301, "start_date": "2016-03-07T02:12:00Z"}, {"corporation_id": 1000009, "record_id": 40693623, "start_date": "2016-01-06T10:39:00Z"}, {"corporation_id": 98340758, "record_id": 39647700, "start_date": "2015-10-02T16:13:00Z"}, {"corporation_id": 1000009, "record_id": 39595402, "start_date": "2015-09-27T16:18:00Z"}, {"corporation_id": 98107045, "is_deleted": true, "record_id": 33073527, "start_date": "2014-05-26T20:18:00Z"}, {"corporation_id": 1000009, "record_id": 33072014, "start_date": "2014-05-26T19:08:00Z"}, {"corporation_id": 1119395129, "record_id": 25502469, "start_date": "2013-05-23T19:59:00Z"}, {"corporation_id": 1000009, "record_id": 25489595, "start_date": "2013-05-23T08:07:00Z"}, {"corporation_id": 300513850, "record_id": 24184194, "start_date": "2013-03-13T20:56:00Z"}, {"corporation_id": 1000044, "record_id": 24027802, "start_date": "2013-03-05T22:13:00Z"}]