[{"corporation_id": 1000060, "record_id": 50981263, "start_date": "2019-10-31T22:27:00Z"}, {"corporation_id": 98252033, "record_id": 45802098, "start_date": "2017-09-10T20:35:00Z"}, {"corporation_id": 1000060, "record_id": 42096359, "start_date": "2016-05-26T08:41:00Z"}, {"corporation_id": 1297486126, "record_id": 38110456, "start_date": "2015-05-14T20:16:00Z"}, {"corporation_id": 1000060, "record_id": 37260917, "start_date": "2015-03-01T09:38:00Z"}, {"corporation_id": 98041262, "record_id": 33401178, "start_date": "2014-06-14T17:08:00Z"}, {"corporation_id": 1000060, "record_id": 33394690, "start_date": "2014-06-14T09:08:00Z"}, {"corporation_id": 98252033, "record_id": 29929734, "start_date": "2013-12-16T14:59:00Z"}, {"corporation_id": 1000172, "record_id": 25472228, "start_date": "2013-05-22T18:41:00Z"}]