[{"corporation_id": 98591576, "record_id": 52557678, "start_date": "2020-04-26T14:22:00Z"}, {"corporation_id": 1000014, "record_id": 52555623, "start_date": "2020-04-26T10:50:00Z"}, {"corporation_id": 98380171, "record_id": 38085277, "start_date": "2015-05-12T01:34:00Z"}, {"corporation_id": 1000014, "record_id": 38085264, "start_date": "2015-05-12T01:33:00Z"}, {"corporation_id": 98260508, "record_id": 36471273, "start_date": "2014-12-28T14:39:00Z"}, {"corporation_id": 1000167, "record_id": 32704056, "start_date": "2014-05-08T00:08:00Z"}]