[{"corporation_id": 1000066, "record_id": 50956143, "start_date": "2019-10-27T20:56:00Z"}, {"corporation_id": 1817710684, "record_id": 49623582, "start_date": "2019-04-01T07:50:00Z"}, {"corporation_id": 177654637, "record_id": 47118505, "start_date": "2018-03-07T08:27:00Z"}, {"corporation_id": 1000066, "record_id": 47118481, "start_date": "2018-03-07T08:24:00Z"}, {"corporation_id": 98380820, "record_id": 46442354, "start_date": "2017-12-07T07:16:00Z"}, {"corporation_id": 1000066, "record_id": 46442344, "start_date": "2017-12-07T07:14:00Z"}, {"corporation_id": 98471665, "record_id": 46190949, "start_date": "2017-11-02T14:20:00Z"}, {"corporation_id": 1000066, "record_id": 46190946, "start_date": "2017-11-02T14:19:00Z"}, {"corporation_id": 98380820, "record_id": 45400860, "start_date": "2017-07-08T06:58:00Z"}, {"corporation_id": 1000066, "record_id": 45390440, "start_date": "2017-07-06T09:18:00Z"}, {"corporation_id": 98471665, "record_id": 42966805, "start_date": "2016-11-04T08:54:00Z"}, {"corporation_id": 1000066, "record_id": 42961180, "start_date": "2016-11-03T09:34:00Z"}, {"corporation_id": 98380820, "record_id": 38173255, "start_date": "2015-05-21T07:03:00Z"}, {"corporation_id": 1000066, "record_id": 38166872, "start_date": "2015-05-20T14:44:00Z"}, {"corporation_id": 98380820, "record_id": 37327722, "start_date": "2015-03-07T05:16:00Z"}, {"corporation_id": 1000066, "record_id": 37327710, "start_date": "2015-03-07T05:14:00Z"}, {"corporation_id": 98246616, "record_id": 34215546, "start_date": "2014-07-28T11:27:00Z"}, {"corporation_id": 1000166, "record_id": 33888827, "start_date": "2014-07-11T12:12:00Z"}]