[{"corporation_id": 1000107, "record_id": 44215285, "start_date": "2017-02-07T09:19:00Z"}, {"corporation_id": 98380820, "record_id": 39566312, "start_date": "2015-09-25T08:56:00Z"}, {"corporation_id": 1000107, "record_id": 39126820, "start_date": "2015-08-17T23:53:00Z"}, {"corporation_id": 98351924, "record_id": 35600838, "start_date": "2014-10-25T01:34:00Z"}, {"corporation_id": 1000107, "record_id": 35600128, "start_date": "2014-10-25T00:31:00Z"}, {"corporation_id": 98007161, "record_id": 35522434, "start_date": "2014-10-19T00:15:00Z"}, {"corporation_id": 1000115, "record_id": 34128092, "start_date": "2014-07-24T08:33:00Z"}]