[{"corporation_id": 98472700, "record_id": 51535329, "start_date": "2020-01-07T07:44:00Z"}, {"corporation_id": 98584891, "is_deleted": true, "record_id": 49088577, "start_date": "2019-01-02T21:59:00Z"}, {"corporation_id": 98552981, "record_id": 48094575, "start_date": "2018-07-28T04:57:00Z"}, {"corporation_id": 98330748, "record_id": 46960121, "start_date": "2018-02-12T01:46:00Z"}, {"corporation_id": 1000046, "record_id": 46960118, "start_date": "2018-02-12T01:46:00Z"}, {"corporation_id": 98437177, "record_id": 46460116, "start_date": "2017-12-09T03:15:00Z"}, {"corporation_id": 98169165, "record_id": 46150502, "start_date": "2017-10-28T18:20:00Z"}, {"corporation_id": 98393608, "is_deleted": true, "record_id": 45606981, "start_date": "2017-08-11T04:31:00Z"}, {"corporation_id": 1000046, "record_id": 45606968, "start_date": "2017-08-11T04:29:00Z"}, {"corporation_id": 98477764, "record_id": 45487091, "start_date": "2017-07-22T22:01:00Z"}, {"corporation_id": 1000046, "record_id": 45487088, "start_date": "2017-07-22T22:01:00Z"}, {"corporation_id": 98393608, "is_deleted": true, "record_id": 44995606, "start_date": "2017-05-11T04:19:00Z"}, {"corporation_id": 98388312, "record_id": 41511256, "start_date": "2016-03-30T19:45:00Z"}, {"corporation_id": 98420757, "is_deleted": true, "record_id": 40768042, "start_date": "2016-01-12T10:43:00Z"}, {"corporation_id": 1000046, "record_id": 40767968, "start_date": "2016-01-12T10:24:00Z"}, {"corporation_id": 98402500, "record_id": 40250716, "start_date": "2015-11-29T21:22:00Z"}, {"corporation_id": 1000046, "record_id": 39996519, "start_date": "2015-11-04T06:29:00Z"}, {"corporation_id": 98107258, "record_id": 39863919, "start_date": "2015-10-23T02:32:00Z"}, {"corporation_id": 98393608, "is_deleted": true, "record_id": 39828070, "start_date": "2015-10-19T03:05:00Z"}, {"corporation_id": 98421428, "record_id": 39705826, "start_date": "2015-10-08T00:19:00Z"}, {"corporation_id": 1000046, "record_id": 39705784, "start_date": "2015-10-08T00:14:00Z"}, {"corporation_id": 98402500, "record_id": 38502862, "start_date": "2015-06-24T05:31:00Z"}, {"corporation_id": 1000046, "record_id": 38502618, "start_date": "2015-06-24T04:36:00Z"}, {"corporation_id": 98169165, "record_id": 38122926, "start_date": "2015-05-16T02:41:00Z"}, {"corporation_id": 1000046, "record_id": 37978901, "start_date": "2015-05-02T03:47:00Z"}, {"corporation_id": 98393608, "is_deleted": true, "record_id": 37932106, "start_date": "2015-04-27T06:09:00Z"}, {"corporation_id": 1000046, "record_id": 37920208, "start_date": "2015-04-26T07:45:00Z"}, {"corporation_id": 98388312, "record_id": 37886319, "start_date": "2015-04-23T03:05:00Z"}, {"corporation_id": 1000046, "record_id": 37886309, "start_date": "2015-04-23T03:04:00Z"}, {"corporation_id": 98169165, "record_id": 35963129, "start_date": "2014-11-22T22:12:00Z"}, {"corporation_id": 1000172, "record_id": 35949772, "start_date": "2014-11-22T05:11:00Z"}]