[{"corporation_id": 1000049, "record_id": 47616614, "start_date": "2018-05-17T10:55:00Z"}, {"corporation_id": 98040755, "record_id": 47152473, "start_date": "2018-03-12T03:21:00Z"}, {"corporation_id": 1000049, "record_id": 47152472, "start_date": "2018-03-12T03:21:00Z"}, {"corporation_id": 98323182, "record_id": 46429474, "start_date": "2017-12-06T03:43:00Z"}, {"corporation_id": 1000049, "record_id": 45830097, "start_date": "2017-09-15T03:57:00Z"}, {"corporation_id": 98040755, "record_id": 40351061, "start_date": "2015-12-10T09:21:00Z"}, {"corporation_id": 1000171, "record_id": 39939322, "start_date": "2015-10-30T08:32:00Z"}]