[{"corporation_id": 98600992, "record_id": 54100341, "start_date": "2020-10-15T18:23:00Z"}, {"corporation_id": 1000111, "record_id": 54053371, "start_date": "2020-10-09T19:51:00Z"}, {"corporation_id": 98604604, "record_id": 52445843, "start_date": "2020-04-16T20:08:00Z"}, {"corporation_id": 1000111, "record_id": 52424572, "start_date": "2020-04-14T20:41:00Z"}, {"corporation_id": 1000180, "record_id": 52228554, "start_date": "2020-03-29T23:36:00Z"}, {"corporation_id": 1000111, "record_id": 49553950, "start_date": "2019-03-20T22:32:00Z"}, {"corporation_id": 98553095, "record_id": 49527304, "start_date": "2019-03-16T16:42:00Z"}, {"corporation_id": 1000111, "record_id": 49527299, "start_date": "2019-03-16T16:42:00Z"}, {"corporation_id": 98578642, "record_id": 48958415, "start_date": "2018-12-12T16:28:00Z"}, {"corporation_id": 1000111, "record_id": 48958247, "start_date": "2018-12-12T15:52:00Z"}, {"corporation_id": 98553095, "record_id": 48940106, "start_date": "2018-12-09T20:26:00Z"}, {"corporation_id": 1000111, "record_id": 48939821, "start_date": "2018-12-09T19:42:00Z"}, {"corporation_id": 98582068, "is_deleted": true, "record_id": 48863032, "start_date": "2018-11-27T05:49:00Z"}, {"corporation_id": 1000111, "record_id": 47523023, "start_date": "2018-05-04T02:42:00Z"}, {"corporation_id": 98370861, "record_id": 42264038, "start_date": "2016-06-22T17:21:00Z"}, {"corporation_id": 1000111, "record_id": 42260036, "start_date": "2016-06-21T20:19:00Z"}, {"corporation_id": 98280133, "record_id": 42228050, "start_date": "2016-06-15T21:26:00Z"}, {"corporation_id": 98464595, "record_id": 42222607, "start_date": "2016-06-14T19:48:00Z"}, {"corporation_id": 1000111, "record_id": 41804964, "start_date": "2016-04-27T14:10:00Z"}, {"corporation_id": 98430447, "record_id": 40658469, "start_date": "2016-01-03T13:52:00Z"}, {"corporation_id": 1000111, "record_id": 40658446, "start_date": "2016-01-03T13:50:00Z"}, {"corporation_id": 98436322, "record_id": 40640533, "start_date": "2016-01-02T03:31:00Z"}, {"corporation_id": 1000111, "record_id": 40640492, "start_date": "2016-01-02T03:27:00Z"}, {"corporation_id": 98434437, "record_id": 40507734, "start_date": "2015-12-22T15:38:00Z"}, {"corporation_id": 1000168, "record_id": 40337422, "start_date": "2015-12-09T05:53:00Z"}]