[{"corporation_id": 1000045, "record_id": 55252972, "start_date": "2021-03-08T04:51:00Z"}, {"corporation_id": 98668715, "record_id": 55033363, "start_date": "2021-02-11T08:08:00Z"}, {"corporation_id": 1000006, "record_id": 52921113, "start_date": "2020-06-01T13:22:00Z"}, {"corporation_id": 98316453, "record_id": 52250276, "start_date": "2020-04-01T01:07:00Z"}, {"corporation_id": 1000006, "record_id": 47999391, "start_date": "2018-07-13T20:39:00Z"}, {"corporation_id": 98523546, "record_id": 47259643, "start_date": "2018-03-28T05:39:00Z"}, {"corporation_id": 1000006, "record_id": 45556400, "start_date": "2017-08-03T00:36:00Z"}, {"corporation_id": 98413418, "record_id": 44662680, "start_date": "2017-03-31T13:13:00Z"}, {"corporation_id": 1000006, "record_id": 44645923, "start_date": "2017-03-29T05:15:00Z"}, {"corporation_id": 98505830, "is_deleted": true, "record_id": 44560559, "start_date": "2017-03-19T03:02:00Z"}, {"corporation_id": 1000006, "record_id": 44560555, "start_date": "2017-03-19T03:01:00Z"}, {"corporation_id": 208504056, "record_id": 44299546, "start_date": "2017-02-17T05:29:00Z"}, {"corporation_id": 98413418, "record_id": 44169162, "start_date": "2017-02-03T03:29:00Z"}, {"corporation_id": 1000006, "record_id": 43994891, "start_date": "2017-01-16T06:32:00Z"}, {"corporation_id": 98413418, "record_id": 42953932, "start_date": "2016-11-01T23:43:00Z"}, {"corporation_id": 1000006, "record_id": 42945162, "start_date": "2016-10-31T11:53:00Z"}, {"corporation_id": 98432863, "record_id": 41749894, "start_date": "2016-04-22T06:59:00Z"}, {"corporation_id": 1000045, "record_id": 41722976, "start_date": "2016-04-19T04:19:00Z"}]