[{"corporation_id": 1000115, "record_id": 54685295, "start_date": "2020-12-31T22:51:00Z"}, {"corporation_id": 98115742, "record_id": 49515858, "start_date": "2019-03-14T21:43:00Z"}, {"corporation_id": 1000111, "record_id": 49433535, "start_date": "2019-02-28T20:29:00Z"}, {"corporation_id": 98040755, "record_id": 46946751, "start_date": "2018-02-10T12:52:00Z"}, {"corporation_id": 1000111, "record_id": 46946731, "start_date": "2018-02-10T12:50:00Z"}, {"corporation_id": 98115742, "record_id": 45899377, "start_date": "2017-09-23T18:18:00Z"}, {"corporation_id": 1000111, "record_id": 45899376, "start_date": "2017-09-23T18:18:00Z"}, {"corporation_id": 98240487, "record_id": 45558940, "start_date": "2017-08-03T13:23:00Z"}, {"corporation_id": 1000111, "record_id": 45558939, "start_date": "2017-08-03T13:23:00Z"}, {"corporation_id": 98040755, "record_id": 45434007, "start_date": "2017-07-14T03:08:00Z"}, {"corporation_id": 1000111, "record_id": 45434005, "start_date": "2017-07-14T03:08:00Z"}, {"corporation_id": 98240487, "record_id": 44952216, "start_date": "2017-05-06T01:23:00Z"}, {"corporation_id": 1000115, "record_id": 43204320, "start_date": "2016-11-21T02:59:00Z"}]